renput/__init__.py
renput-0.0.4.dist-info/LICENSE
renput-0.0.4.dist-info/METADATA
renput-0.0.4.dist-info/WHEEL
renput-0.0.4.dist-info/top_level.txt
renput-0.0.4.dist-info/RECORD
