Metadata-Version: 2.1
Name: renput
Version: 0.0.4
Summary: Tab-completion for inputs
Home-page: UNKNOWN
Author: Jaegerwald (JaegerwaldDev)
Author-email: <jaegerwald.dev@gmail.com>
License: UNKNOWN
Keywords: tab,completion,auto-completion,tab-completion,input,modified input,windows,easy-to-use
Platform: UNKNOWN
Classifier: Development Status :: 2 - Pre-Alpha
Classifier: Intended Audience :: Developers
Classifier: Programming Language :: Python :: 3
Classifier: Operating System :: Microsoft :: Windows
License-File: LICENSE
